pyqt_vertical_tab_widget/__init__.py
pyqt_vertical_tab_widget/verticalTabWidget.py
pyqt_vertical_tab_widget-0.0.12.dist-info/LICENSE
pyqt_vertical_tab_widget-0.0.12.dist-info/METADATA
pyqt_vertical_tab_widget-0.0.12.dist-info/WHEEL
pyqt_vertical_tab_widget-0.0.12.dist-info/top_level.txt
pyqt_vertical_tab_widget-0.0.12.dist-info/RECORD
