Metadata-Version: 2.1
Name: pyqt-vertical-tab-widget
Version: 0.0.12
Summary: PyQt vertical tab widget (text is horizontal)
Home-page: https://github.com/yjg30737/pyqt-vertical-tab-widget.git
Author: Jung Gyu Yoon
Author-email: yjg30737@gmail.com
License: MIT
License-File: LICENSE
Requires-Dist: PyQt5 (>=5.8)
